remote_gource/__init__.py
remote_gource-0.0.1.dist-info/LICENCE
remote_gource-0.0.1.dist-info/METADATA
remote_gource-0.0.1.dist-info/WHEEL
remote_gource-0.0.1.dist-info/top_level.txt
remote_gource-0.0.1.dist-info/RECORD
